copyrightextractor/__init__.py
copyrightextractor/copyrightextractor.py
copyrightextractor-0.0.0.dist-info/DESCRIPTION.rst
copyrightextractor-0.0.0.dist-info/METADATA
copyrightextractor-0.0.0.dist-info/RECORD
copyrightextractor-0.0.0.dist-info/WHEEL
copyrightextractor-0.0.0.dist-info/metadata.json
copyrightextractor-0.0.0.dist-info/top_level.txt
