Metadata-Version: 2.0
Name: copyrightextractor
Version: 0.0.0
Summary: Extract copyright from HTML content
Home-page: https://github.com/samaybhavsar/copyrightextractor
Author: Samay Bhavsar
Author-email: samay@samay.info
License: UNKNOWN
Keywords: copyright extractor html
Platform: UNKNOWN
Classifier: Development Status :: 3 - Alpha
Classifier: Intended Audience :: Developers
Classifier: Topic :: Software Development :: Build Tools
Classifier: License :: OSI Approved :: MIT License
Classifier: Programming Language :: Python :: 2.7
